README.md
setup.py
GameOfLife/__init__.py
GameOfLife/gameoflife.py
GameOfLife/patterns.py
pp_gameoflife.egg-info/PKG-INFO
pp_gameoflife.egg-info/SOURCES.txt
pp_gameoflife.egg-info/dependency_links.txt
pp_gameoflife.egg-info/top_level.txt