Metadata-Version: 1.0
Name: pp-gameoflife
Version: 2.0
Summary: Custom game of life implementation
Home-page: https://github.com/PhilippPilar/ASPP-project/GameOfLife
Author: Philipp Pilar
Author-email: philipp.pilar@it.uu.se
License: BSD
Platform: UNKNOWN
